poem_fa/__init__.py
poem_fa/hafez.db
poem_fa/hafez.py
poem_fa/main.py
poem_fa/utils.py
poem_fa-0.3.0.dist-info/LICENSE
poem_fa-0.3.0.dist-info/METADATA
poem_fa-0.3.0.dist-info/WHEEL
poem_fa-0.3.0.dist-info/entry_points.txt
poem_fa-0.3.0.dist-info/RECORD
