Metadata-Version: 2.1
Name: poem-fa
Version: 0.3.0
Summary: 
Author: Mehdi Ghodsizadeh
Author-email: m.ghodsizadeh@gmail.com
Requires-Python: >=3.8,<4.0
Classifier: Programming Language :: Python :: 3
Classifier: Programming Language :: Python :: 3.8
Classifier: Programming Language :: Python :: 3.9
Classifier: Programming Language :: Python :: 3.10
Classifier: Programming Language :: Python :: 3.11
Requires-Dist: arabic-reshaper (>=3.0.0,<4.0.0)
Requires-Dist: python-bidi (>=0.4.2,<0.5.0)
Requires-Dist: typer (>=0.9.0,<0.10.0)
